LICENSE
README.md
pyproject.toml
agentauth_mcp/__init__.py
venv/lib/python3.13/site-packages/build-1.2.2.post1.dist-info/LICENSE
venv/lib/python3.13/site-packages/certifi-2025.6.15.dist-info/licenses/LICENSE
venv/lib/python3.13/site-packages/charset_normalizer-3.4.2.dist-info/licenses/LICENSE
venv/lib/python3.13/site-packages/id-1.5.0.dist-info/LICENSE
venv/lib/python3.13/site-packages/jaraco.classes-3.4.0.dist-info/LICENSE
venv/lib/python3.13/site-packages/jaraco.context-6.0.1.dist-info/LICENSE
venv/lib/python3.13/site-packages/jaraco_functools-4.2.1.dist-info/licenses/LICENSE
venv/lib/python3.13/site-packages/keyring-25.6.0.dist-info/LICENSE
venv/lib/python3.13/site-packages/markdown_it_py-3.0.0.dist-info/LICENSE
venv/lib/python3.13/site-packages/mdurl-0.1.2.dist-info/LICENSE
venv/lib/python3.13/site-packages/more_itertools-10.7.0.dist-info/LICENSE
venv/lib/python3.13/site-packages/nh3-0.2.21.dist-info/licenses/LICENSE
venv/lib/python3.13/site-packages/packaging-25.0.dist-info/licenses/LICENSE
venv/lib/python3.13/site-packages/pathspec-0.12.1.dist-info/LICENSE
venv/lib/python3.13/site-packages/pluggy-1.6.0.dist-info/licenses/LICENSE
venv/lib/python3.13/site-packages/pygments-2.19.2.dist-info/licenses/LICENSE
venv/lib/python3.13/site-packages/pyproject_hooks-1.2.0.dist-info/LICENSE
venv/lib/python3.13/site-packages/readme_renderer-44.0.dist-info/LICENSE
venv/lib/python3.13/site-packages/requests-2.32.4.dist-info/licenses/LICENSE
venv/lib/python3.13/site-packages/requests_toolbelt-1.0.0.dist-info/LICENSE
venv/lib/python3.13/site-packages/rfc3986-2.0.0.dist-info/LICENSE
venv/lib/python3.13/site-packages/rich-14.0.0.dist-info/LICENSE
venv/lib/python3.13/site-packages/trove_classifiers-2025.5.9.12.dist-info/licenses/LICENSE
venv/lib/python3.13/site-packages/twine-6.1.0.dist-info/LICENSE
agentauth_mcp-0.0.1.dev0.dist-info/METADATA
agentauth_mcp-0.0.1.dev0.dist-info/WHEEL
agentauth_mcp-0.0.1.dev0.dist-info/licenses/LICENSE
agentauth_mcp-0.0.1.dev0.dist-info/RECORD
