Metadata-Version: 2.4
Name: agentauth-mcp
Version: 0.0.1.dev0
Summary: Reserved project name for future AgentAuth MCP.
Project-URL: Homepage, https://agentauth.co
Author-email: AgentAuth <developers@agentauth.co>
License: This package is proprietary and not licensed for redistribution or reuse.
License-File: LICENSE
Keywords: agentauth,ai-agents,authentication,cli,command-line,connector,identity,mcp,mcp-clients,mcp-servers,model-context-protocol,proxy,terminal
Classifier: Development Status :: 1 - Planning
Classifier: License :: Other/Proprietary License
Classifier: Programming Language :: Python :: 3
Requires-Python: >=3.8
